{
  "updated_at": "2026-07-08 13:22:19",
  "updated_epoch": 1783484539,
  "source": "live",
  "summary": {
    "server_count": 64,
    "total_ccu": 2514
  },
  "servers": [
    {
      "num": "1M312",
      "name": "(1M312) GAME_8000",
      "type": "GS",
      "ccu": 39,
      "condition": "OPEN",
      "fps_min": 121,
      "fps_avg": 132,
      "fps_max": 137,
      "fps": 129,
      "cpu": 15.9,
      "used_mem": 17022920,
      "wait_dispatch": 0,
      "dispatched": 22,
      "in_packets": 22,
      "connections": 39
    },
    {
      "num": "1M365",
      "name": "(1M365) GAME_8400",
      "type": "GS",
      "ccu": 37,
      "condition": "OPEN",
      "fps_min": 120,
      "fps_avg": 133,
      "fps_max": 139,
      "fps": 132,
      "cpu": 8.2,
      "used_mem": 14147380,
      "wait_dispatch": 0,
      "dispatched": 9,
      "in_packets": 4,
      "connections": 37
    },
    {
      "num": "1M384",
      "name": "(1M384) GAME_8000",
      "type": "GS",
      "ccu": 62,
      "condition": "OPEN",
      "fps_min": 125,
      "fps_avg": 131,
      "fps_max": 137,
      "fps": 125,
      "cpu": 30.0,
      "used_mem": 19381128,
      "wait_dispatch": 0,
      "dispatched": 22,
      "in_packets": 18,
      "connections": 62
    },
    {
      "num": "1M389",
      "name": "(1M389) GAME_8100",
      "type": "GS",
      "ccu": 18,
      "condition": "OPEN",
      "fps_min": 135,
      "fps_avg": 137,
      "fps_max": 141,
      "fps": 140,
      "cpu": 28.4,
      "used_mem": 12630752,
      "wait_dispatch": 0,
      "dispatched": 0,
      "in_packets": 0,
      "connections": 18
    },
    {
      "num": "1M411",
      "name": "(1M411) GAME_8000",
      "type": "GS",
      "ccu": 197,
      "condition": "OPEN",
      "fps_min": 87,
      "fps_avg": 110,
      "fps_max": 120,
      "fps": 120,
      "cpu": 28.4,
      "used_mem": 27467764,
      "wait_dispatch": 1,
      "dispatched": 49,
      "in_packets": 54,
      "connections": 198
    },
    {
      "num": "1M436",
      "name": "(1M436) GAME_8300",
      "type": "GS",
      "ccu": 39,
      "condition": "OPEN",
      "fps_min": 119,
      "fps_avg": 129,
      "fps_max": 135,
      "fps": 119,
      "cpu": 7.9,
      "used_mem": 13556436,
      "wait_dispatch": 0,
      "dispatched": 9,
      "in_packets": 9,
      "connections": 39
    },
    {
      "num": "1M440",
      "name": "(1M440) GAME_8200",
      "type": "GS",
      "ccu": 50,
      "condition": "OPEN",
      "fps_min": 119,
      "fps_avg": 131,
      "fps_max": 139,
      "fps": 132,
      "cpu": 9.0,
      "used_mem": 20439732,
      "wait_dispatch": 3,
      "dispatched": 408,
      "in_packets": 423,
      "connections": 49
    },
    {
      "num": "1M451",
      "name": "(1M451) GAME_8000",
      "type": "GS",
      "ccu": 65,
      "condition": "OPEN",
      "fps_min": 99,
      "fps_avg": 118,
      "fps_max": 128,
      "fps": 128,
      "cpu": 100.0,
      "used_mem": 25488300,
      "wait_dispatch": 0,
      "dispatched": 4,
      "in_packets": 4,
      "connections": 65
    },
    {
      "num": "1M452",
      "name": "(1M452) GAME_8000",
      "type": "GS",
      "ccu": 62,
      "condition": "OPEN",
      "fps_min": 106,
      "fps_avg": 129,
      "fps_max": 136,
      "fps": 130,
      "cpu": 8.0,
      "used_mem": 22792524,
      "wait_dispatch": 0,
      "dispatched": 36,
      "in_packets": 36,
      "connections": 63
    },
    {
      "num": "1M453",
      "name": "(1M453) GAME_8100",
      "type": "GS",
      "ccu": 68,
      "condition": "OPEN",
      "fps_min": 107,
      "fps_avg": 129,
      "fps_max": 135,
      "fps": 133,
      "cpu": 18.8,
      "used_mem": 20400076,
      "wait_dispatch": 0,
      "dispatched": 19,
      "in_packets": 19,
      "connections": 69
    },
    {
      "num": "1M454",
      "name": "(1M454) GAME_8100",
      "type": "GS",
      "ccu": 202,
      "condition": "OPEN",
      "fps_min": 75,
      "fps_avg": 107,
      "fps_max": 119,
      "fps": 119,
      "cpu": 23.7,
      "used_mem": 26711712,
      "wait_dispatch": 0,
      "dispatched": 724,
      "in_packets": 541,
      "connections": 201
    },
    {
      "num": "1M455",
      "name": "(1M455) GAME_8200",
      "type": "GS",
      "ccu": 41,
      "condition": "OPEN",
      "fps_min": 131,
      "fps_avg": 134,
      "fps_max": 139,
      "fps": 132,
      "cpu": 18.8,
      "used_mem": 17537404,
      "wait_dispatch": 0,
      "dispatched": 4,
      "in_packets": 4,
      "connections": 41
    },
    {
      "num": "1M456",
      "name": "(1M456) GAME_8000",
      "type": "GS",
      "ccu": 39,
      "condition": "OPEN",
      "fps_min": 116,
      "fps_avg": 132,
      "fps_max": 139,
      "fps": 135,
      "cpu": 11.2,
      "used_mem": 18241352,
      "wait_dispatch": 0,
      "dispatched": 344,
      "in_packets": 113,
      "connections": 39
    },
    {
      "num": "1M457",
      "name": "(1M457) GAME_8100",
      "type": "GS",
      "ccu": 66,
      "condition": "OPEN",
      "fps_min": 123,
      "fps_avg": 129,
      "fps_max": 137,
      "fps": 131,
      "cpu": 10.6,
      "used_mem": 18774616,
      "wait_dispatch": 0,
      "dispatched": 447,
      "in_packets": 442,
      "connections": 66
    },
    {
      "num": "1M458",
      "name": "(1M458) GAME_8100",
      "type": "GS",
      "ccu": 50,
      "condition": "OPEN",
      "fps_min": 110,
      "fps_avg": 126,
      "fps_max": 135,
      "fps": 128,
      "cpu": 30.0,
      "used_mem": 18985200,
      "wait_dispatch": 0,
      "dispatched": 39,
      "in_packets": 34,
      "connections": 51
    },
    {
      "num": "1M459",
      "name": "(1M459) GAME_8000",
      "type": "GS",
      "ccu": 33,
      "condition": "OPEN",
      "fps_min": 136,
      "fps_avg": 139,
      "fps_max": 141,
      "fps": 139,
      "cpu": 23.3,
      "used_mem": 13766780,
      "wait_dispatch": 0,
      "dispatched": 300,
      "in_packets": 300,
      "connections": 33
    },
    {
      "num": "1M462",
      "name": "(1M462) GAME_8100",
      "type": "GS",
      "ccu": 27,
      "condition": "OPEN",
      "fps_min": 127,
      "fps_avg": 135,
      "fps_max": 140,
      "fps": 133,
      "cpu": 45.5,
      "used_mem": 14134592,
      "wait_dispatch": 0,
      "dispatched": 4,
      "in_packets": 4,
      "connections": 27
    },
    {
      "num": "1M486",
      "name": "(1M486) GAME_8100",
      "type": "GS",
      "ccu": 84,
      "condition": "OPEN",
      "fps_min": 96,
      "fps_avg": 120,
      "fps_max": 126,
      "fps": 96,
      "cpu": 100.0,
      "used_mem": 22464368,
      "wait_dispatch": 0,
      "dispatched": 9,
      "in_packets": 9,
      "connections": 84
    },
    {
      "num": "1M487",
      "name": "(1M487) GAME_8100",
      "type": "GS",
      "ccu": 57,
      "condition": "OPEN",
      "fps_min": 119,
      "fps_avg": 125,
      "fps_max": 132,
      "fps": 128,
      "cpu": 10.3,
      "used_mem": 17571072,
      "wait_dispatch": 0,
      "dispatched": 59,
      "in_packets": 59,
      "connections": 57
    },
    {
      "num": "1M488",
      "name": "(1M488) GAME_8300",
      "type": "GS",
      "ccu": 45,
      "condition": "OPEN",
      "fps_min": 134,
      "fps_avg": 137,
      "fps_max": 140,
      "fps": 136,
      "cpu": 8.2,
      "used_mem": 10652432,
      "wait_dispatch": 0,
      "dispatched": 19,
      "in_packets": 19,
      "connections": 45
    },
    {
      "num": "1M489",
      "name": "(1M489) GAME_8000",
      "type": "GS",
      "ccu": 44,
      "condition": "OPEN",
      "fps_min": 130,
      "fps_avg": 133,
      "fps_max": 136,
      "fps": 130,
      "cpu": 92.7,
      "used_mem": 18393400,
      "wait_dispatch": 0,
      "dispatched": 4,
      "in_packets": 4,
      "connections": 44
    },
    {
      "num": "1M490",
      "name": "(1M490) GAME_8000",
      "type": "GS",
      "ccu": 46,
      "condition": "OPEN",
      "fps_min": 133,
      "fps_avg": 134,
      "fps_max": 136,
      "fps": 136,
      "cpu": 9.1,
      "used_mem": 17583712,
      "wait_dispatch": 0,
      "dispatched": 14,
      "in_packets": 14,
      "connections": 46
    },
    {
      "num": "1M491",
      "name": "(1M491) GAME_8300",
      "type": "GS",
      "ccu": 18,
      "condition": "OPEN",
      "fps_min": 126,
      "fps_avg": 140,
      "fps_max": 143,
      "fps": 143,
      "cpu": 44.7,
      "used_mem": 8393896,
      "wait_dispatch": 0,
      "dispatched": 4,
      "in_packets": 4,
      "connections": 18
    },
    {
      "num": "1M492",
      "name": "(1M492) GAME_8400",
      "type": "GS",
      "ccu": 12,
      "condition": "OPEN",
      "fps_min": 139,
      "fps_avg": 141,
      "fps_max": 142,
      "fps": 142,
      "cpu": 74.4,
      "used_mem": 8295116,
      "wait_dispatch": 0,
      "dispatched": 4,
      "in_packets": 4,
      "connections": 12
    },
    {
      "num": "1M493",
      "name": "(1M493) GAME_8000",
      "type": "GS",
      "ccu": 26,
      "condition": "OPEN",
      "fps_min": 137,
      "fps_avg": 139,
      "fps_max": 141,
      "fps": 141,
      "cpu": 8.9,
      "used_mem": 10315532,
      "wait_dispatch": 0,
      "dispatched": 29,
      "in_packets": 29,
      "connections": 26
    },
    {
      "num": "1M494",
      "name": "(1M494) GAME_8200",
      "type": "GS",
      "ccu": 16,
      "condition": "OPEN",
      "fps_min": 137,
      "fps_avg": 140,
      "fps_max": 142,
      "fps": 139,
      "cpu": 7.7,
      "used_mem": 8764304,
      "wait_dispatch": 0,
      "dispatched": 4,
      "in_packets": 4,
      "connections": 16
    },
    {
      "num": "1M495",
      "name": "(1M495) GAME_8100",
      "type": "GS",
      "ccu": 10,
      "condition": "OPEN",
      "fps_min": 140,
      "fps_avg": 142,
      "fps_max": 143,
      "fps": 143,
      "cpu": 52.1,
      "used_mem": 8371624,
      "wait_dispatch": 0,
      "dispatched": 0,
      "in_packets": 0,
      "connections": 10
    },
    {
      "num": "1M496",
      "name": "(1M496) GAME_8100",
      "type": "GS",
      "ccu": 38,
      "condition": "OPEN",
      "fps_min": 129,
      "fps_avg": 134,
      "fps_max": 137,
      "fps": 129,
      "cpu": 26.0,
      "used_mem": 14163072,
      "wait_dispatch": 0,
      "dispatched": 156,
      "in_packets": 156,
      "connections": 38
    },
    {
      "num": "1M497",
      "name": "(1M497) GAME_8100",
      "type": "GS",
      "ccu": 25,
      "condition": "OPEN",
      "fps_min": 128,
      "fps_avg": 134,
      "fps_max": 138,
      "fps": 136,
      "cpu": 11.7,
      "used_mem": 11131436,
      "wait_dispatch": 0,
      "dispatched": 348,
      "in_packets": 343,
      "connections": 25
    },
    {
      "num": "1M498",
      "name": "(1M498) GAME_8000",
      "type": "GS",
      "ccu": 9,
      "condition": "OPEN",
      "fps_min": 139,
      "fps_avg": 141,
      "fps_max": 142,
      "fps": 142,
      "cpu": 22.6,
      "used_mem": 7408344,
      "wait_dispatch": 0,
      "dispatched": 4,
      "in_packets": 4,
      "connections": 9
    },
    {
      "num": "1M68",
      "name": "(1M68) GAME_8000",
      "type": "GS",
      "ccu": 28,
      "condition": "OPEN",
      "fps_min": 134,
      "fps_avg": 138,
      "fps_max": 140,
      "fps": 138,
      "cpu": 74.4,
      "used_mem": 15790028,
      "wait_dispatch": 0,
      "dispatched": 39,
      "in_packets": 39,
      "connections": 28
    },
    {
      "num": "1M78",
      "name": "(1M78) GAME_8100",
      "type": "GS",
      "ccu": 62,
      "condition": "OPEN",
      "fps_min": 127,
      "fps_avg": 132,
      "fps_max": 137,
      "fps": 131,
      "cpu": 17.4,
      "used_mem": 17937360,
      "wait_dispatch": 0,
      "dispatched": 19,
      "in_packets": 19,
      "connections": 62
    },
    {
      "num": "1M81",
      "name": "(1M81) GAME_8400",
      "type": "GS",
      "ccu": 49,
      "condition": "OPEN",
      "fps_min": 74,
      "fps_avg": 123,
      "fps_max": 133,
      "fps": 124,
      "cpu": 83.3,
      "used_mem": 19168148,
      "wait_dispatch": 0,
      "dispatched": 14,
      "in_packets": 14,
      "connections": 49
    },
    {
      "num": "1M83",
      "name": "(1M83) GAME_8200",
      "type": "GS",
      "ccu": 53,
      "condition": "OPEN",
      "fps_min": 126,
      "fps_avg": 132,
      "fps_max": 137,
      "fps": 133,
      "cpu": 10.1,
      "used_mem": 18123012,
      "wait_dispatch": 0,
      "dispatched": 4,
      "in_packets": 4,
      "connections": 51
    },
    {
      "num": "1M85",
      "name": "(1M85) GAME_8000",
      "type": "GS",
      "ccu": 113,
      "condition": "OPEN",
      "fps_min": 115,
      "fps_avg": 124,
      "fps_max": 128,
      "fps": 123,
      "cpu": 8.6,
      "used_mem": 33340764,
      "wait_dispatch": 0,
      "dispatched": 54,
      "in_packets": 54,
      "connections": 113
    },
    {
      "num": "1M86",
      "name": "(1M86) GAME_8100",
      "type": "GS",
      "ccu": 120,
      "condition": "OPEN",
      "fps_min": 124,
      "fps_avg": 129,
      "fps_max": 136,
      "fps": 128,
      "cpu": 77.6,
      "used_mem": 15635844,
      "wait_dispatch": 0,
      "dispatched": 24,
      "in_packets": 24,
      "connections": 120
    },
    {
      "num": "1M87",
      "name": "(1M87) GAME_8000",
      "type": "GS",
      "ccu": 78,
      "condition": "OPEN",
      "fps_min": 120,
      "fps_avg": 129,
      "fps_max": 136,
      "fps": 131,
      "cpu": 8.6,
      "used_mem": 22074788,
      "wait_dispatch": 0,
      "dispatched": 14,
      "in_packets": 14,
      "connections": 78
    },
    {
      "num": "1M88",
      "name": "(1M88) GAME_8100",
      "type": "GS",
      "ccu": 109,
      "condition": "OPEN",
      "fps_min": 99,
      "fps_avg": 108,
      "fps_max": 116,
      "fps": 100,
      "cpu": 12.2,
      "used_mem": 26752036,
      "wait_dispatch": 0,
      "dispatched": 49,
      "in_packets": 49,
      "connections": 108
    },
    {
      "num": "L472",
      "name": "(L472) GAME_8200",
      "type": "GS",
      "ccu": 4,
      "condition": "OPEN",
      "fps_min": 140,
      "fps_avg": 142,
      "fps_max": 143,
      "fps": 141,
      "cpu": 74.4,
      "used_mem": 6716340,
      "wait_dispatch": 0,
      "dispatched": 4,
      "in_packets": 4,
      "connections": 4
    },
    {
      "num": "L473",
      "name": "(L473) GAME_8300",
      "type": "GS",
      "ccu": 2,
      "condition": "OPEN",
      "fps_min": 141,
      "fps_avg": 142,
      "fps_max": 142,
      "fps": 142,
      "cpu": 9.6,
      "used_mem": 6623188,
      "wait_dispatch": 0,
      "dispatched": 0,
      "in_packets": 0,
      "connections": 2
    },
    {
      "num": "L474",
      "name": "(L474) GAME_8000",
      "type": "GS",
      "ccu": 2,
      "condition": "OPEN",
      "fps_min": 140,
      "fps_avg": 141,
      "fps_max": 143,
      "fps": 142,
      "cpu": 23.2,
      "used_mem": 6534180,
      "wait_dispatch": 0,
      "dispatched": 0,
      "in_packets": 0,
      "connections": 2
    },
    {
      "num": "L475",
      "name": "(L475) GAME_8100",
      "type": "GS",
      "ccu": 4,
      "condition": "OPEN",
      "fps_min": 141,
      "fps_avg": 142,
      "fps_max": 143,
      "fps": 142,
      "cpu": 13.6,
      "used_mem": 6709808,
      "wait_dispatch": 0,
      "dispatched": 0,
      "in_packets": 0,
      "connections": 4
    },
    {
      "num": "L476",
      "name": "(L476) GAME_8200",
      "type": "GS",
      "ccu": 3,
      "condition": "OPEN",
      "fps_min": 141,
      "fps_avg": 142,
      "fps_max": 143,
      "fps": 142,
      "cpu": 8.4,
      "used_mem": 7471220,
      "wait_dispatch": 0,
      "dispatched": 0,
      "in_packets": 0,
      "connections": 3
    },
    {
      "num": "L477",
      "name": "(L477) GAME_8200",
      "type": "GS",
      "ccu": 8,
      "condition": "OPEN",
      "fps_min": 140,
      "fps_avg": 141,
      "fps_max": 142,
      "fps": 142,
      "cpu": 11.4,
      "used_mem": 7904096,
      "wait_dispatch": 0,
      "dispatched": 118,
      "in_packets": 118,
      "connections": 8
    },
    {
      "num": "L478",
      "name": "(L478) GAME_8200",
      "type": "GS",
      "ccu": 10,
      "condition": "OPEN",
      "fps_min": 137,
      "fps_avg": 139,
      "fps_max": 142,
      "fps": 138,
      "cpu": 8.9,
      "used_mem": 7902480,
      "wait_dispatch": 0,
      "dispatched": 9,
      "in_packets": 9,
      "connections": 10
    },
    {
      "num": "L479",
      "name": "(L479) GAME_8300",
      "type": "GS",
      "ccu": 2,
      "condition": "OPEN",
      "fps_min": 142,
      "fps_avg": 143,
      "fps_max": 143,
      "fps": 142,
      "cpu": 34.3,
      "used_mem": 6511140,
      "wait_dispatch": 0,
      "dispatched": 83,
      "in_packets": 83,
      "connections": 2
    },
    {
      "num": "L480",
      "name": "(L480) GAME_8300",
      "type": "GS",
      "ccu": 3,
      "condition": "OPEN",
      "fps_min": 141,
      "fps_avg": 142,
      "fps_max": 143,
      "fps": 143,
      "cpu": 9.3,
      "used_mem": 6625160,
      "wait_dispatch": 1,
      "dispatched": 108,
      "in_packets": 113,
      "connections": 3
    },
    {
      "num": "L481",
      "name": "(L481) GAME_8200",
      "type": "GS",
      "ccu": 6,
      "condition": "OPEN",
      "fps_min": 137,
      "fps_avg": 140,
      "fps_max": 141,
      "fps": 140,
      "cpu": 11.5,
      "used_mem": 6774436,
      "wait_dispatch": 0,
      "dispatched": 19,
      "in_packets": 19,
      "connections": 5
    },
    {
      "num": "L482",
      "name": "(L482) GAME_8300",
      "type": "GS",
      "ccu": 7,
      "condition": "OPEN",
      "fps_min": 140,
      "fps_avg": 142,
      "fps_max": 143,
      "fps": 142,
      "cpu": 100.0,
      "used_mem": 7230160,
      "wait_dispatch": 0,
      "dispatched": 0,
      "in_packets": 0,
      "connections": 7
    },
    {
      "num": "L483",
      "name": "(L483) GAME_8000",
      "type": "GS",
      "ccu": 9,
      "condition": "OPEN",
      "fps_min": 138,
      "fps_avg": 141,
      "fps_max": 142,
      "fps": 142,
      "cpu": 8.5,
      "used_mem": 7206672,
      "wait_dispatch": 0,
      "dispatched": 0,
      "in_packets": 0,
      "connections": 9
    },
    {
      "num": "L484",
      "name": "(L484) GAME_8300",
      "type": "GS",
      "ccu": 9,
      "condition": "OPEN",
      "fps_min": 140,
      "fps_avg": 142,
      "fps_max": 143,
      "fps": 142,
      "cpu": 74.4,
      "used_mem": 7430148,
      "wait_dispatch": 0,
      "dispatched": 0,
      "in_packets": 0,
      "connections": 9
    },
    {
      "num": "L485",
      "name": "(L485) GAME_8300",
      "type": "GS",
      "ccu": 8,
      "condition": "OPEN",
      "fps_min": 141,
      "fps_avg": 142,
      "fps_max": 142,
      "fps": 142,
      "cpu": 16.1,
      "used_mem": 7795008,
      "wait_dispatch": 0,
      "dispatched": 4,
      "in_packets": 4,
      "connections": 8
    },
    {
      "num": "L499",
      "name": "(L499) GAME_8400",
      "type": "GS",
      "ccu": 14,
      "condition": "OPEN",
      "fps_min": 140,
      "fps_avg": 141,
      "fps_max": 142,
      "fps": 141,
      "cpu": 9.7,
      "used_mem": 8777840,
      "wait_dispatch": 0,
      "dispatched": 159,
      "in_packets": 159,
      "connections": 14
    },
    {
      "num": "L500",
      "name": "(L500) GAME_8200",
      "type": "GS",
      "ccu": 22,
      "condition": "OPEN",
      "fps_min": 138,
      "fps_avg": 141,
      "fps_max": 143,
      "fps": 141,
      "cpu": 15.6,
      "used_mem": 9426992,
      "wait_dispatch": 0,
      "dispatched": 14,
      "in_packets": 14,
      "connections": 22
    },
    {
      "num": "L501",
      "name": "(L501) GAME_8000",
      "type": "GS",
      "ccu": 6,
      "condition": "OPEN",
      "fps_min": 139,
      "fps_avg": 141,
      "fps_max": 142,
      "fps": 141,
      "cpu": 8.0,
      "used_mem": 8489936,
      "wait_dispatch": 0,
      "dispatched": 13,
      "in_packets": 13,
      "connections": 6
    },
    {
      "num": "L502",
      "name": "(L502) GAME_8100",
      "type": "GS",
      "ccu": 13,
      "condition": "OPEN",
      "fps_min": 125,
      "fps_avg": 139,
      "fps_max": 143,
      "fps": 141,
      "cpu": 24.5,
      "used_mem": 8868396,
      "wait_dispatch": 0,
      "dispatched": 4,
      "in_packets": 4,
      "connections": 13
    },
    {
      "num": "L503",
      "name": "(L503) GAME_8100",
      "type": "GS",
      "ccu": 17,
      "condition": "OPEN",
      "fps_min": 127,
      "fps_avg": 140,
      "fps_max": 142,
      "fps": 142,
      "cpu": 17.4,
      "used_mem": 8647660,
      "wait_dispatch": 0,
      "dispatched": 4,
      "in_packets": 4,
      "connections": 17
    },
    {
      "num": "L504",
      "name": "(L504) GAME_8200",
      "type": "GS",
      "ccu": 15,
      "condition": "OPEN",
      "fps_min": 141,
      "fps_avg": 142,
      "fps_max": 143,
      "fps": 142,
      "cpu": 39.1,
      "used_mem": 9387656,
      "wait_dispatch": 0,
      "dispatched": 0,
      "in_packets": 0,
      "connections": 15
    },
    {
      "num": "L505",
      "name": "(L505) GAME_8200",
      "type": "GS",
      "ccu": 17,
      "condition": "OPEN",
      "fps_min": 118,
      "fps_avg": 138,
      "fps_max": 142,
      "fps": 118,
      "cpu": 16.8,
      "used_mem": 9667596,
      "wait_dispatch": 0,
      "dispatched": 4,
      "in_packets": 4,
      "connections": 17
    },
    {
      "num": "L506",
      "name": "(L506) GAME_8200",
      "type": "GS",
      "ccu": 22,
      "condition": "OPEN",
      "fps_min": 139,
      "fps_avg": 140,
      "fps_max": 142,
      "fps": 139,
      "cpu": 9.2,
      "used_mem": 10323372,
      "wait_dispatch": 0,
      "dispatched": 27,
      "in_packets": 27,
      "connections": 22
    },
    {
      "num": "L507",
      "name": "(L507) GAME_8100",
      "type": "GS",
      "ccu": 42,
      "condition": "OPEN",
      "fps_min": 126,
      "fps_avg": 137,
      "fps_max": 139,
      "fps": 137,
      "cpu": 13.7,
      "used_mem": 10956112,
      "wait_dispatch": 1,
      "dispatched": 24,
      "in_packets": 29,
      "connections": 41
    },
    {
      "num": "L508",
      "name": "(L508) GAME_8200",
      "type": "GS",
      "ccu": 108,
      "condition": "OPEN",
      "fps_min": 136,
      "fps_avg": 138,
      "fps_max": 140,
      "fps": 138,
      "cpu": 30.9,
      "used_mem": 16971416,
      "wait_dispatch": 0,
      "dispatched": 224,
      "in_packets": 220,
      "connections": 109
    },
    {
      "num": "L700",
      "name": "(L700) GAME_8000",
      "type": "GS",
      "ccu": 6,
      "condition": "OPEN",
      "fps_min": 140,
      "fps_avg": 142,
      "fps_max": 142,
      "fps": 142,
      "cpu": 8.0,
      "used_mem": 1531204,
      "wait_dispatch": 1,
      "dispatched": 4,
      "in_packets": 9,
      "connections": 6
    },
    {
      "num": "L750",
      "name": "(L750) GAME_8300",
      "type": "GS",
      "ccu": 18,
      "condition": "OPEN",
      "fps_min": 135,
      "fps_avg": 138,
      "fps_max": 140,
      "fps": 139,
      "cpu": 13.8,
      "used_mem": 2095992,
      "wait_dispatch": 0,
      "dispatched": 267,
      "in_packets": 267,
      "connections": 18
    }
  ],
  "alerts": [
    {
      "id": "crash:LG056|GS|(1M86) GAME_8100:1783477285:LG056_GS__1M86__GAME8100_CRASH_DUMP__GameServer_Payment__2026-07-08__01-37-48",
      "level": "crash",
      "since": 1783477285,
      "text": "🚨 LG056|GS|(1M86) GAME_8100 — Access Violation (메모리 접근 위반) @ 0x00007FF6D002963D"
    },
    {
      "id": "evt:1M86:16871113",
      "level": "err",
      "since": 1783474710,
      "text": "(1M86) GAME_8100: 11 서버 연결됨!!!"
    },
    {
      "id": "evt:1M86:16871110",
      "level": "err",
      "since": 1783474700,
      "text": "(1M86) GAME_8100: 11 서버 끊어짐!!!"
    },
    {
      "id": "crash:LWG01|GS|(L700) GAME_8000:1783473036:LWG01_GS__L700__GAME8000_CRASH_DUMP__GameServer_Payment__2026-07-08__01-08-35",
      "level": "crash",
      "since": 1783473036,
      "text": "🚨 LWG01|GS|(L700) GAME_8000 — Unknown Exception (0x00000000) @ (unknown)"
    },
    {
      "id": "evt:L700:16871107",
      "level": "err",
      "since": 1783472934,
      "text": "(L700) GAME_8000: 11 서버 연결됨!!!"
    },
    {
      "id": "evt:L750:16871106",
      "level": "err",
      "since": 1783472934,
      "text": "(L750) GAME_8300: 11 서버 연결됨!!!"
    },
    {
      "id": "evt:L700:16871103",
      "level": "err",
      "since": 1783472924,
      "text": "(L700) GAME_8000: 11 서버 끊어짐!!!"
    },
    {
      "id": "evt:L750:16871102",
      "level": "err",
      "since": 1783472919,
      "text": "(L750) GAME_8300: 11 서버 끊어짐!!!"
    },
    {
      "id": "crash:LG047|GS|(1M488) GAME_8300:1783371339:LG047_GS__1M488__GAME8300_CRASH_DUMP__GameServer_Payment__2026-07-06__20-15-34",
      "level": "crash",
      "since": 1783371339,
      "text": "🚨 LG047|GS|(1M488) GAME_8300 — Access Violation (메모리 접근 위반) @ 0x00007FF687A6963D"
    }
  ],
  "crashes": [
    {
      "id": "crash:LG056|GS|(1M86) GAME_8100:1783477285:LG056_GS__1M86__GAME8100_CRASH_DUMP__GameServer_Payment__2026-07-08__01-37-48",
      "since": 1783477285,
      "server": "LG056|GS|(1M86) GAME_8100",
      "version": "GS_Payment_20260630_1004",
      "exception": "Access Violation (메모리 접근 위반)",
      "location": "0x00007FF6D002963D",
      "source": null,
      "source_code": [
        "  0: 037> cdb: Reading initial command '$$<C:\\Users\\potc-server\\AppData\\Local\\Temp\\cdb_script_c3c4fc0c-6571-4cd2-9feb-58d442276827.txt'",
        "  0: 037> .lines -e",
        "  0: 037> .ecxr",
        "  0: 037> kn 30",
        "  0: 037> lsa .",
        "  2523: logReason = DB_LOG::REASON_GUILD_BUILD_REPAIR;",
        "  2524: ",
        "  2525: if (pGuildBuildInfo->IsProtectMode() && nullptr != pUser)",
        "  2526: {",
        "> 2527: Captcha::CCaptchaManager::Instance()->CheckFortressRepairCaptcha(pGuild->GetGuildID(), _ack->UserID());",
        "  2528: }",
        "  2529: ",
        "  2530: pGuildBuildInfo->DisposTime = 0;",
        "  2531: }",
        "  2532: else"
      ],
      "call_stack": [
        "#00 CGameWorker::OnRecv_DB_FIELD_OBJECT_GUILD_UPDATE_ACK at GameWorker_DBA.cpp:2527",
        "#01 CGameWorker::OnDispatch_DBA at GameWorker_DBA.cpp:504",
        "#02 CGameWorker::_on_dispatch at GameWorker.cpp:130",
        "#03 CGameWorker::OnDispatch at GameWorker.cpp:108",
        "#04 TLNET::CNetWorker::_run_on_dispatch at NetWorker.cpp:179",
        "#05 TLNET::CNetWorker::Run_ALL at NetWorker.cpp:52",
        "#06 boost::_mfi::mf0<void,TLNET::CNetWorker>::operator() at mem_fn_template.hpp:49",
        "#07 boost::_bi::list1<boost::_bi::value<TLNET::CNetWorker *> >::operator()<boost::_mfi::mf0<void,TLNET::CNetWorker>,boost::_bi::list0> at bind.hpp:239",
        "#08 boost::_bi::bind_t<void,boost::_mfi::mf0<void,TLNET::CNetWorker>,boost::_bi::list1<boost::_bi::value<TLNET::CNetWorker *> > >::operator() at bind.hpp:1274",
        "#09 boost::detail::thread_data<boost::_bi::bind_t<void,boost::_mfi::mf0<void,TLNET::CNetCore>,boost::_bi::list1<boost::_bi::value<TLNET::CNetCore *> > > >::run at thread.hpp:120"
      ],
      "dump": "LG056_GS__1M86__GAME8100_CRASH_DUMP__GameServer_Payment__2026-07-08__01-37-48.dmp",
      "time": "2026-07-08 01:37:48",
      "report_md": "## 🚨 Crash — LG056|GS|(1M86) GAME_8100\n- **Server**: LG056|GS|(1M86) GAME_8100\n- **Version**: GS_Payment_20260630_1004\n- **Exception**: Access Violation (메모리 접근 위반)\n- **Location**: 0x00007FF6D002963D\n- **Time**: 2026-07-08 01:37:48\n- **Dump**: LG056_GS__1M86__GAME8100_CRASH_DUMP__GameServer_Payment__2026-07-08__01-37-48.dmp\n\n### Exception code\n```\n  0: 037> cdb: Reading initial command '$$<C:\\Users\\potc-server\\AppData\\Local\\Temp\\cdb_script_c3c4fc0c-6571-4cd2-9feb-58d442276827.txt'\n  0: 037> .lines -e\n  0: 037> .ecxr\n  0: 037> kn 30\n  0: 037> lsa .\n  2523: logReason = DB_LOG::REASON_GUILD_BUILD_REPAIR;\n  2524: \n  2525: if (pGuildBuildInfo->IsProtectMode() && nullptr != pUser)\n  2526: {\n> 2527: Captcha::CCaptchaManager::Instance()->CheckFortressRepairCaptcha(pGuild->GetGuildID(), _ack->UserID());\n  2528: }\n  2529: \n  2530: pGuildBuildInfo->DisposTime = 0;\n  2531: }\n  2532: else\n```\n\n### Call stack\n```\n#00 CGameWorker::OnRecv_DB_FIELD_OBJECT_GUILD_UPDATE_ACK at GameWorker_DBA.cpp:2527\n#01 CGameWorker::OnDispatch_DBA at GameWorker_DBA.cpp:504\n#02 CGameWorker::_on_dispatch at GameWorker.cpp:130\n#03 CGameWorker::OnDispatch at GameWorker.cpp:108\n#04 TLNET::CNetWorker::_run_on_dispatch at NetWorker.cpp:179\n#05 TLNET::CNetWorker::Run_ALL at NetWorker.cpp:52\n#06 boost::_mfi::mf0<void,TLNET::CNetWorker>::operator() at mem_fn_template.hpp:49\n#07 boost::_bi::list1<boost::_bi::value<TLNET::CNetWorker *> >::operator()<boost::_mfi::mf0<void,TLNET::CNetWorker>,boost::_bi::list0> at bind.hpp:239\n#08 boost::_bi::bind_t<void,boost::_mfi::mf0<void,TLNET::CNetWorker>,boost::_bi::list1<boost::_bi::value<TLNET::CNetWorker *> > >::operator() at bind.hpp:1274\n#09 boost::detail::thread_data<boost::_bi::bind_t<void,boost::_mfi::mf0<void,TLNET::CNetCore>,boost::_bi::list1<boost::_bi::value<TLNET::CNetCore *> > > >::run at thread.hpp:120\n```\n"
    },
    {
      "id": "crash:LWG01|GS|(L700) GAME_8000:1783473036:LWG01_GS__L700__GAME8000_CRASH_DUMP__GameServer_Payment__2026-07-08__01-08-35",
      "since": 1783473036,
      "server": "LWG01|GS|(L700) GAME_8000",
      "version": "GS_Payment_20260630_1004",
      "exception": "Unknown Exception (0x00000000)",
      "location": "(unknown)",
      "source": null,
      "source_code": [],
      "call_stack": [],
      "dump": "LWG01_GS__L700__GAME8000_CRASH_DUMP__GameServer_Payment__2026-07-08__01-08-35.dmp",
      "time": "2026-07-08 01:08:35",
      "report_md": "## 🚨 Crash — LWG01|GS|(L700) GAME_8000\n- **Server**: LWG01|GS|(L700) GAME_8000\n- **Version**: GS_Payment_20260630_1004\n- **Exception**: Unknown Exception (0x00000000)\n- **Location**: (unknown)\n- **Time**: 2026-07-08 01:08:35\n- **Dump**: LWG01_GS__L700__GAME8000_CRASH_DUMP__GameServer_Payment__2026-07-08__01-08-35.dmp\n"
    },
    {
      "id": "crash:LG047|GS|(1M488) GAME_8300:1783371339:LG047_GS__1M488__GAME8300_CRASH_DUMP__GameServer_Payment__2026-07-06__20-15-34",
      "since": 1783371339,
      "server": "LG047|GS|(1M488) GAME_8300",
      "version": "GS_Payment_20260630_1004",
      "exception": "Access Violation (메모리 접근 위반)",
      "location": "0x00007FF687A6963D",
      "source": null,
      "source_code": [
        "  0: 037> cdb: Reading initial command '$$<C:\\Users\\potc-server\\AppData\\Local\\Temp\\cdb_script_e5c5cbb3-c130-4a72-9667-0ea3d353aa86.txt'",
        "  0: 037> .lines -e",
        "  0: 037> .ecxr",
        "  0: 037> kn 30",
        "  0: 037> lsa .",
        "  2523: logReason = DB_LOG::REASON_GUILD_BUILD_REPAIR;",
        "  2524: ",
        "  2525: if (pGuildBuildInfo->IsProtectMode() && nullptr != pUser)",
        "  2526: {",
        "> 2527: Captcha::CCaptchaManager::Instance()->CheckFortressRepairCaptcha(pGuild->GetGuildID(), _ack->UserID());",
        "  2528: }",
        "  2529: ",
        "  2530: pGuildBuildInfo->DisposTime = 0;",
        "  2531: }",
        "  2532: else"
      ],
      "call_stack": [
        "#00 CGameWorker::OnRecv_DB_FIELD_OBJECT_GUILD_UPDATE_ACK at GameWorker_DBA.cpp:2527",
        "#01 CGameWorker::OnDispatch_DBA at GameWorker_DBA.cpp:504",
        "#02 CGameWorker::_on_dispatch at GameWorker.cpp:130",
        "#03 CGameWorker::OnDispatch at GameWorker.cpp:108",
        "#04 TLNET::CNetWorker::_run_on_dispatch at NetWorker.cpp:179",
        "#05 TLNET::CNetWorker::Run_ALL at NetWorker.cpp:52",
        "#06 boost::_mfi::mf0<void,TLNET::CNetWorker>::operator() at mem_fn_template.hpp:49",
        "#07 boost::_bi::list1<boost::_bi::value<TLNET::CNetWorker *> >::operator()<boost::_mfi::mf0<void,TLNET::CNetWorker>,boost::_bi::list0> at bind.hpp:239",
        "#08 boost::_bi::bind_t<void,boost::_mfi::mf0<void,TLNET::CNetWorker>,boost::_bi::list1<boost::_bi::value<TLNET::CNetWorker *> > >::operator() at bind.hpp:1274",
        "#09 boost::detail::thread_data<boost::_bi::bind_t<void,boost::_mfi::mf0<void,TLNET::CNetCore>,boost::_bi::list1<boost::_bi::value<TLNET::CNetCore *> > > >::run at thread.hpp:120"
      ],
      "dump": "LG047_GS__1M488__GAME8300_CRASH_DUMP__GameServer_Payment__2026-07-06__20-15-34.dmp",
      "time": "2026-07-06 20:15:34",
      "report_md": "## 🚨 Crash — LG047|GS|(1M488) GAME_8300\n- **Server**: LG047|GS|(1M488) GAME_8300\n- **Version**: GS_Payment_20260630_1004\n- **Exception**: Access Violation (메모리 접근 위반)\n- **Location**: 0x00007FF687A6963D\n- **Time**: 2026-07-06 20:15:34\n- **Dump**: LG047_GS__1M488__GAME8300_CRASH_DUMP__GameServer_Payment__2026-07-06__20-15-34.dmp\n\n### Exception code\n```\n  0: 037> cdb: Reading initial command '$$<C:\\Users\\potc-server\\AppData\\Local\\Temp\\cdb_script_e5c5cbb3-c130-4a72-9667-0ea3d353aa86.txt'\n  0: 037> .lines -e\n  0: 037> .ecxr\n  0: 037> kn 30\n  0: 037> lsa .\n  2523: logReason = DB_LOG::REASON_GUILD_BUILD_REPAIR;\n  2524: \n  2525: if (pGuildBuildInfo->IsProtectMode() && nullptr != pUser)\n  2526: {\n> 2527: Captcha::CCaptchaManager::Instance()->CheckFortressRepairCaptcha(pGuild->GetGuildID(), _ack->UserID());\n  2528: }\n  2529: \n  2530: pGuildBuildInfo->DisposTime = 0;\n  2531: }\n  2532: else\n```\n\n### Call stack\n```\n#00 CGameWorker::OnRecv_DB_FIELD_OBJECT_GUILD_UPDATE_ACK at GameWorker_DBA.cpp:2527\n#01 CGameWorker::OnDispatch_DBA at GameWorker_DBA.cpp:504\n#02 CGameWorker::_on_dispatch at GameWorker.cpp:130\n#03 CGameWorker::OnDispatch at GameWorker.cpp:108\n#04 TLNET::CNetWorker::_run_on_dispatch at NetWorker.cpp:179\n#05 TLNET::CNetWorker::Run_ALL at NetWorker.cpp:52\n#06 boost::_mfi::mf0<void,TLNET::CNetWorker>::operator() at mem_fn_template.hpp:49\n#07 boost::_bi::list1<boost::_bi::value<TLNET::CNetWorker *> >::operator()<boost::_mfi::mf0<void,TLNET::CNetWorker>,boost::_bi::list0> at bind.hpp:239\n#08 boost::_bi::bind_t<void,boost::_mfi::mf0<void,TLNET::CNetWorker>,boost::_bi::list1<boost::_bi::value<TLNET::CNetWorker *> > >::operator() at bind.hpp:1274\n#09 boost::detail::thread_data<boost::_bi::bind_t<void,boost::_mfi::mf0<void,TLNET::CNetCore>,boost::_bi::list1<boost::_bi::value<TLNET::CNetCore *> > > >::run at thread.hpp:120\n```\n"
    }
  ],
  "maint": false,
  "maint_manual": false
}